breadcrumbsaddressbar/__init__.py
breadcrumbsaddressbar/breadcrumbsaddressbar.py
breadcrumbsaddressbar/iconfinder_icon-ios7-arrow-left_211689.png
breadcrumbsaddressbar/iconfinder_icon-ios7-arrow-right_211607.png
breadcrumbsaddressbar/layouts.py
breadcrumbsaddressbar/models_views.py
breadcrumbsaddressbar/py.typed
breadcrumbsaddressbar/stylesheet.py
breadcrumbsaddressbar/platform/common.py
breadcrumbsaddressbar/platform/windows.py
breadcrumbsaddressbar-0.1.0.dev0.dist-info/METADATA
breadcrumbsaddressbar-0.1.0.dev0.dist-info/WHEEL
breadcrumbsaddressbar-0.1.0.dev0.dist-info/licenses/LICENSE
breadcrumbsaddressbar-0.1.0.dev0.dist-info/RECORD
