Metadata-Version: 2.4
Name: breadcrumbsaddressbar
Version: 0.1.0.dev0
Summary: Address bar Qt widget with breadcrumb navigation
Author-email: Andrey Makarov <winandfx@gmail.com>
License-File: LICENSE
Requires-Python: >=3.12
Requires-Dist: pywin32>=308; sys_platform == 'win32'
Requires-Dist: qtpy>=2.4.3
